README.md
setup.py
qmplot/__init__.py
qmplot/main.py
qmplot.egg-info/PKG-INFO
qmplot.egg-info/SOURCES.txt
qmplot.egg-info/dependency_links.txt
qmplot.egg-info/entry_points.txt
qmplot.egg-info/requires.txt
qmplot.egg-info/top_level.txt
qmplot/modules/__init__.py
qmplot/modules/_manhattan.py
qmplot/modules/_qq.py
qmplot/utils/__init__.py
qmplot/utils/_adjust_text.py
qmplot/utils/_misc.py